{
  "typeform": [{
      "dia": "2021-06-29",
      "nombre": "Jhon",
      "apellido": "Wickc",
      "telefono": "3042757600"
  },{
      "dia": "2021-06-29",
      "nombre": "Bryan",
      "apellido": "Foronda",
      "telefono": "3042757600"
  },{
      "dia": "2021-06-29",
      "nombre": "Bryan",
      "apellido": "Foronda",
      "telefono": "3042757600"
  },{
      "dia": "2021-06-29",
      "nombre": "Bryan",
      "apellido": "Foronda",
      "telefono": "3042757600"
  },{
      "dia": "2021-06-29",
      "nombre": "Bryan",
      "apellido": "Foronda",
      "telefono": "3042757600"
  },{
      "dia": "2021-06-29",
      "nombre": "Bryan",
      "apellido": "Foronda",
      "telefono": "3042757600"
  },{
      "dia": "2021-06-29",
      "nombre": "Bryan",
      "apellido": "Foronda",
      "telefono": "3042757600"
  },{
      "dia": "2021-06-29",
      "nombre": "Bryan",
      "apellido": "Foronda",
      "telefono": "3042757600"
  },{
      "dia": "2021-06-29",
      "nombre": "Bryan",
      "apellido": "Foronda",
      "telefono": "3042757600"
  },{
      "dia": "2021-06-29",
      "nombre": "Bryan",
      "apellido": "Foronda",
      "telefono": "3042757600"
  },{
      "dia": "2021-06-29",
      "nombre": "Bryan",
      "apellido": "Foronda",
      "telefono": "3042757600"
  },{
      "dia": "2021-06-29",
      "nombre": "Bryan",
      "apellido": "Foronda",
      "telefono": "3042757600"
  },{
      "dia": "2021-06-29",
      "nombre": "Bryan",
      "apellido": "Foronda",
      "telefono": "3042757600"
  }],
  "goals": [{
      "startDate": "2021-07-02T05:00:00.000Z", 
      "endDate": "2021-07-02T05:00:00.000Z"
  }],
  "facebook": [{
    "fecha": '2021-06-29',
    "inversion": 30000,
    "impresiones": 30,
    "cpm": 33,
    "clics": 300,
    "ctr": 30,
    "cpc": 6,
  },
  {
    "fecha": '2021-06-29',
    "inversion": 100000,
    "impresiones": 455,
    "cpm": 443,
    "clics": 430,
    "ctr": 230,
    "cpc": 120,
  }],
  "dashboard": [{
      "fecha": "2021-06-29",
      "inversion_rounded": 5,
      "impresiones": 505,
      "cpm": 344,
      "clics": 1035,
      "ctr": 322,
      "cpc": 123,
      "views": 264,
      "leads": 172,
      "%cr": 11,
      "cpl": 37,
      "repr": 173,
      "clicsVimeo": 174, 
      "%clicsVimeo": 16,
      "aps": 455,
      "%aps": 26,
      "cpap": 146,
      "lead-ap": 850,
      "agenda": 136,
      "qses": 125,
      "%qses": 15,
      "cpqses": 453,
      "asist": 153,
      "%asist": 12,
      "cpses": 457,
      "bhmsales": 273,
      "%bhmscr": 23,
      "cac_bhm": 465,
      "bhmrevenue": 4566,
      "bhmcash": 78444,
      "%a-r": 23,
      "bhm_acv": 7338,
      "#NQses": 22,
      "abhsales": 738,
      "abhSCR": 1231,
      "abhrevenue": 626,
      "abhcash": 1178,
      "abhA/R": 44,
      "abhACV": 332,
      "a6csales": 1222,
      "a6cSCR": 3365,
      "a6crevenue": 755,
      "a6ccash": 111,
      "a6cA/R": 455,
      "$a6cACV": 33,
      "cmsales": 126,
      "cmSCR": 765,
      "cmrevenue": 4455,
      "cmcash": 3446,
      "cmA/R": 566,
      "$cmACV": 12,
      "dwACV": 2335,
      "%dwSCR": 15,
      "TotalRevenue": 4122,
      "ProfitR": 12444,
      "TotalCash": 3400,
      "ProfitC": 34445,
      "TotalA/R": 124000,
      "ROIRevenue": 4355,
      "ROICash": 453,
      "EPCRevenue": 2262,
      "EPCCash": 3445,
      "EPLRevenue": 12363,
      "EPLCash": 5677,
      "EPApRevenue": 2336,
      "EPApCash": 56666,
      "%FCR": 45,
      "cac-rdw": 87700,
      "cac-cdw": 6550
  },{
      "fecha": "2021-06-29",
      "inversion_rounded": 5,
      "impresiones": 50,
      "cpm": 34,
      "clics": 105,
      "ctr": 32,
      "cpc": 12,
      "views": 24,
      "leads": 12,
      "%cr": 11,
      "cpl": 3,
      "repr": 13,
      "clicsVimeo": 14, 
      "%clicsVimeo": 16,
      "aps": 45,
      "%aps": 26,
      "cpap": 14,
      "lead-ap": 50,
      "agenda": 13,
      "qses": 12,
      "%qses": 15,
      "cpqses": 45,
      "asist": 13,
      "%asist": 12,
      "cpses": 45,
      "bhmsales": 23,
      "%bhmscr": 23,
      "cac_bhm": 45,
      "bhmrevenue": 66,
      "bhmcash": 78,
      "%a-r": 23,
      "bhm_acv": 78,
      "#NQses": 22,
      "abhsales": 78,
      "abhSCR": 11,
      "abhrevenue": 66,
      "abhcash": 78,
      "abhA/R": 44,
      "abhACV": 33,
      "a6csales": 12,
      "a6cSCR": 33,
      "a6crevenue": 55,
      "a6ccash": 111,
      "a6cA/R": 455,
      "$a6cACV": 33,
      "cmsales": 12,
      "cmSCR": 76,
      "cmrevenue": 455,
      "cmcash": 344,
      "cmA/R": 566,
      "$cmACV": 12,
      "dwACV": 233,
      "%dwSCR": 15,
      "TotalRevenue": 122,
      "ProfitR": 124,
      "TotalCash": 3400,
      "ProfitC": 3444,
      "TotalA/R": 12000,
      "ROIRevenue": 455,
      "ROICash": 45,
      "EPCRevenue": 222,
      "EPCCash": 3445,
      "EPLRevenue": 1233,
      "EPLCash": 5677,
      "EPApRevenue": 233,
      "EPApCash": 566,
      "%FCR": 45,
      "cac-rdw": 877,
      "cac-cdw": 655
  }]
}
